MANIFEST.in
README.md
setup.py
annotation/hg18_refseq.ucsc
annotation/hg19_refseq.ucsc
annotation/mm10_refseq.ucsc
annotation/mm8_refseq.ucsc
annotation/mm9_refseq.ucsc
pyrose/ROSE_utils.py
pyrose/__init__.py
pyrose/bamToGFF
pyrose/callSuper.R
pyrose/geneMapper
pyrose/helper.py
pyrose/pyrose
pyrose.egg-info/PKG-INFO
pyrose.egg-info/SOURCES.txt
pyrose.egg-info/dependency_links.txt
pyrose.egg-info/top_level.txt