Metadata-Version: 1.1
Name: pyrose
Version: 1.04
Summary: A Python Package for Rank Ordering of Super-Enhancers
Home-page: https://github.com/asntech/pyrose
Author: Aziz Khan
Author-email: khana10@mails.tsinghua.edu.cn
License: UNKNOWN
Platform: UNKNOWN
Classifier: Intended Audience :: Developers
Classifier: Intended Audience :: Science/Research
Classifier: License :: OSI Approved :: MIT License
Classifier: Operating System :: OS Independent
Classifier: Programming Language :: Python :: 2.7
Classifier: Topic :: Scientific/Engineering :: Bio-Informatics
